autoblocks/__init__.py
autoblocks/_impl/__init__.py
autoblocks/_impl/api/__init__.py
autoblocks/_impl/api/app_client.py
autoblocks/_impl/api/base_app_resource_client.py
autoblocks/_impl/api/client.py
autoblocks/_impl/api/exceptions.py
autoblocks/_impl/api/models.py
autoblocks/_impl/api/utils/__init__.py
autoblocks/_impl/api/utils/helpers.py
autoblocks/_impl/api/utils/serialization.py
autoblocks/_impl/app/__init__.py
autoblocks/_impl/app/client.py
autoblocks/_impl/app/models.py
autoblocks/_impl/config/__init__.py
autoblocks/_impl/config/constants.py
autoblocks/_impl/configs/__init__.py
autoblocks/_impl/configs/config.py
autoblocks/_impl/configs/models.py
autoblocks/_impl/context_vars.py
autoblocks/_impl/datasets/__init__.py
autoblocks/_impl/datasets/client.py
autoblocks/_impl/datasets/models/__init__.py
autoblocks/_impl/datasets/models/conversation.py
autoblocks/_impl/datasets/models/dataset.py
autoblocks/_impl/datasets/models/schema.py
autoblocks/_impl/datasets/util.py
autoblocks/_impl/global_state.py
autoblocks/_impl/human_review/__init__.py
autoblocks/_impl/human_review/client.py
autoblocks/_impl/human_review/models.py
autoblocks/_impl/prompts/__init__.py
autoblocks/_impl/prompts/autogenerate.py
autoblocks/_impl/prompts/cli/__init__.py
autoblocks/_impl/prompts/cli/main.py
autoblocks/_impl/prompts/cli/models.py
autoblocks/_impl/prompts/context.py
autoblocks/_impl/prompts/error.py
autoblocks/_impl/prompts/manager.py
autoblocks/_impl/prompts/models.py
autoblocks/_impl/prompts/placeholders.py
autoblocks/_impl/prompts/renderer.py
autoblocks/_impl/prompts/utils.py
autoblocks/_impl/prompts/v2/__init__.py
autoblocks/_impl/prompts/v2/client.py
autoblocks/_impl/prompts/v2/context.py
autoblocks/_impl/prompts/v2/discovery/__init__.py
autoblocks/_impl/prompts/v2/discovery/app_generation.py
autoblocks/_impl/prompts/v2/discovery/code_generator.py
autoblocks/_impl/prompts/v2/discovery/file_utils.py
autoblocks/_impl/prompts/v2/discovery/managers.py
autoblocksai-0.0.137.dist-info/LICENSE
autoblocksai-0.0.137.dist-info/METADATA
autoblocksai-0.0.137.dist-info/WHEEL
autoblocksai-0.0.137.dist-info/entry_points.txt
autoblocksai-0.0.137.dist-info/RECORD
