Metadata-Version: 2.1
Name: autoblocksai
Version: 0.0.137
Summary: Python client for Autoblocks
Home-page: https://github.com/autoblocksai/python-sdk
License: MIT
Author: Autoblocks Engineering
Author-email: engineering@autoblocks.ai
Requires-Python: >=3.9.0,<4.0.0
Classifier: License :: OSI Approved :: MIT License
Classifier: Programming Language :: Python :: 3
Classifier: Programming Language :: Python :: 3.9
Classifier: Programming Language :: Python :: 3.10
Classifier: Programming Language :: Python :: 3.11
Classifier: Programming Language :: Python :: 3.12
Requires-Dist: click (>=8.0.0)
Requires-Dist: cuid2 (>=2.0.0)
Requires-Dist: httpx (>=0.24.0)
Requires-Dist: opentelemetry-api (>=1.0.0)
Requires-Dist: opentelemetry-exporter-otlp-proto-http (>=1.0.0)
Requires-Dist: opentelemetry-sdk (>=1.0.0)
Requires-Dist: orjson (>=3.0.0)
Requires-Dist: pydantic (>=2.11.7)
Requires-Dist: pyyaml (>=6.0.0)
Requires-Dist: tenacity (>=8.0.0)
Project-URL: Documentation, https://docs.autoblocks.ai
Project-URL: Repository, https://github.com/autoblocksai/python-sdk
